odoo/addons/product_attribute_set/README.rst
odoo/addons/product_attribute_set/__init__.py
odoo/addons/product_attribute_set/__manifest__.py
odoo/addons/product_attribute_set/demo/product_attribute.xml
odoo/addons/product_attribute_set/i18n/es.po
odoo/addons/product_attribute_set/i18n/es_AR.po
odoo/addons/product_attribute_set/i18n/product_attribute_set.pot
odoo/addons/product_attribute_set/models/__init__.py
odoo/addons/product_attribute_set/models/product.py
odoo/addons/product_attribute_set/models/product_category.py
odoo/addons/product_attribute_set/readme/CONTRIBUTORS.rst
odoo/addons/product_attribute_set/readme/DESCRIPTION.rst
odoo/addons/product_attribute_set/readme/ROADMAP.rst
odoo/addons/product_attribute_set/readme/USAGE.rst
odoo/addons/product_attribute_set/static/description/icon.png
odoo/addons/product_attribute_set/static/description/index.html
odoo/addons/product_attribute_set/tests/__init__.py
odoo/addons/product_attribute_set/tests/test_product_attribute_set.py
odoo/addons/product_attribute_set/views/product.xml
odoo/addons/product_attribute_set/views/product_category.xml
odoo14_addon_product_attribute_set-14.0.1.1.0.dist-info/METADATA
odoo14_addon_product_attribute_set-14.0.1.1.0.dist-info/WHEEL
odoo14_addon_product_attribute_set-14.0.1.1.0.dist-info/top_level.txt
odoo14_addon_product_attribute_set-14.0.1.1.0.dist-info/RECORD
